gripa/__init__.py
gripa/_hpf.py
gripa/_ssa.py
gripa/base.py
gripa/detector.py
gripa/tests/__init__.py
gripa/tests/test_detector.py
gripa/utils.py
gripa-0.1.3.dist-info/LICENSE
gripa-0.1.3.dist-info/METADATA
gripa-0.1.3.dist-info/WHEEL
gripa-0.1.3.dist-info/RECORD
